whotracksme/__init__.py
whotracksme/main.py
whotracksme/data/__init__.py
whotracksme/data/loader.py
whotracksme/data/assets/trackerdb.sql
whotracksme/data/assets/2017-05/global/companies.csv
whotracksme/data/assets/2017-05/global/domains.csv
whotracksme/data/assets/2017-05/global/sites.csv
whotracksme/data/assets/2017-05/global/sites_trackers.csv
whotracksme/data/assets/2017-05/global/trackers.csv
whotracksme/data/assets/2017-06/global/companies.csv
whotracksme/data/assets/2017-06/global/domains.csv
whotracksme/data/assets/2017-06/global/sites.csv
whotracksme/data/assets/2017-06/global/sites_trackers.csv
whotracksme/data/assets/2017-06/global/trackers.csv
whotracksme/data/assets/2017-07/global/companies.csv
whotracksme/data/assets/2017-07/global/domains.csv
whotracksme/data/assets/2017-07/global/sites.csv
whotracksme/data/assets/2017-07/global/sites_trackers.csv
whotracksme/data/assets/2017-07/global/trackers.csv
whotracksme/data/assets/2017-08/global/companies.csv
whotracksme/data/assets/2017-08/global/domains.csv
whotracksme/data/assets/2017-08/global/sites.csv
whotracksme/data/assets/2017-08/global/sites_trackers.csv
whotracksme/data/assets/2017-08/global/trackers.csv
whotracksme/data/assets/2017-09/global/companies.csv
whotracksme/data/assets/2017-09/global/domains.csv
whotracksme/data/assets/2017-09/global/sites.csv
whotracksme/data/assets/2017-09/global/sites_trackers.csv
whotracksme/data/assets/2017-09/global/trackers.csv
whotracksme/data/assets/2017-10/global/companies.csv
whotracksme/data/assets/2017-10/global/domains.csv
whotracksme/data/assets/2017-10/global/sites.csv
whotracksme/data/assets/2017-10/global/sites_trackers.csv
whotracksme/data/assets/2017-10/global/trackers.csv
whotracksme/data/assets/2017-11/global/companies.csv
whotracksme/data/assets/2017-11/global/domains.csv
whotracksme/data/assets/2017-11/global/sites.csv
whotracksme/data/assets/2017-11/global/sites_trackers.csv
whotracksme-2018.5.17.dist-info/METADATA
whotracksme-2018.5.17.dist-info/RECORD
whotracksme-2018.5.17.dist-info/WHEEL
whotracksme-2018.5.17.dist-info/entry_points.txt
whotracksme-2018.5.17.dist-info/top_level.txt
whotracksme-2018.5.17.dist-info/zip-safe
