Metadata-Version: 2.1
Name: whotracksme
Version: 2018.5.17
Summary: Learn about tracking technologies, market structure and data-sharing on the web
Home-page: https://whotracks.me
Author: Cliqz Gmbh
Author-email: privacy@cliqz.com
License: MIT
Keywords: tracking whotracksme whotracks.me who tracks
Platform: UNKNOWN
Classifier: Development Status :: 4 - Beta
Classifier: Environment :: Console
Classifier: Intended Audience :: Developers
Classifier: Intended Audience :: Information Technology
Classifier: Intended Audience :: Science/Research
Classifier: License :: OSI Approved :: MIT License
Classifier: Operating System :: OS Independent
Classifier: Programming Language :: Python :: 3.6
Classifier: Topic :: Internet
Classifier: Topic :: Scientific/Engineering :: Information Analysis
Provides-Extra: dev
Requires-Dist: docopt
Requires-Dist: pandas
Provides-Extra: dev
Requires-Dist: aiohttp; extra == 'dev'
Requires-Dist: boto3; extra == 'dev'
Requires-Dist: colour; extra == 'dev'
Requires-Dist: jinja2; extra == 'dev'
Requires-Dist: markdown; extra == 'dev'
Requires-Dist: plotly; extra == 'dev'
Requires-Dist: pytest; extra == 'dev'
Requires-Dist: sanic; extra == 'dev'
Requires-Dist: squarify; extra == 'dev'
Requires-Dist: twine; extra == 'dev'
Requires-Dist: watchdog; extra == 'dev'
Requires-Dist: libsass; extra == 'dev'
